cachekaro/__init__.py
cachekaro/__main__.py
cachekaro/cli.py
cachekaro/config/__init__.py
cachekaro/config/default.py
cachekaro/config/paths/__init__.py
cachekaro/core/__init__.py
cachekaro/core/analyzer.py
cachekaro/core/cleaner.py
cachekaro/core/scanner.py
cachekaro/exporters/__init__.py
cachekaro/exporters/base.py
cachekaro/exporters/csv_export.py
cachekaro/exporters/html_export.py
cachekaro/exporters/json_export.py
cachekaro/exporters/text.py
cachekaro/models/__init__.py
cachekaro/models/cache_item.py
cachekaro/models/scan_result.py
cachekaro/platforms/__init__.py
cachekaro/platforms/base.py
cachekaro/platforms/detector.py
cachekaro/platforms/linux.py
cachekaro/platforms/macos.py
cachekaro/platforms/windows.py
cachekaro/utils/__init__.py
cachekaro/utils/colors.py
cachekaro/utils/formatting.py
cachekaro-2.3.0.dist-info/licenses/LICENSE
cachekaro-2.3.0.dist-info/METADATA
cachekaro-2.3.0.dist-info/WHEEL
cachekaro-2.3.0.dist-info/entry_points.txt
cachekaro-2.3.0.dist-info/top_level.txt
cachekaro-2.3.0.dist-info/RECORD
