Metadata-Version: 2.4
Name: cachekaro
Version: 2.3.0
Summary: Cross-platform storage and cache analyzer & cleaner - Cache Karo!
Author-email: MOHIT BAGRI <mailmohitbagri@gmail.com>
Maintainer-email: MOHIT BAGRI <mailmohitbagri@gmail.com>
License-Expression: MIT
Project-URL: Homepage, https://github.com/Mohit-Bagri/cachekaro
Project-URL: Documentation, https://github.com/Mohit-Bagri/cachekaro#readme
Project-URL: Repository, https://github.com/Mohit-Bagri/cachekaro.git
Project-URL: Issues, https://github.com/Mohit-Bagri/cachekaro/issues
Project-URL: Changelog, https://github.com/Mohit-Bagri/cachekaro/blob/main/CHANGELOG.md
Keywords: cache,storage,cleanup,disk-space,system-maintenance,cross-platform,macos,linux,windows
Classifier: Development Status :: 4 - Beta
Classifier: Environment :: Console
Classifier: Intended Audience :: Developers
Classifier: Intended Audience :: System Administrators
Classifier: Intended Audience :: End Users/Desktop
Classifier: Operating System :: OS Independent
Classifier: Operating System :: MacOS :: MacOS X
Classifier: Operating System :: POSIX :: Linux
Classifier: Operating System :: Microsoft :: Windows
Classifier: Programming Language :: Python :: 3
Classifier: Programming Language :: Python :: 3.9
Classifier: Programming Language :: Python :: 3.10
Classifier: Programming Language :: Python :: 3.11
Classifier: Programming Language :: Python :: 3.12
Classifier: Topic :: System :: Systems Administration
Classifier: Topic :: Utilities
Requires-Python: >=3.9
License-File: LICENSE
Requires-Dist: pyyaml>=6.0
Requires-Dist: colorama>=0.4.6
Provides-Extra: dev
Requires-Dist: pytest>=7.0; extra == "dev"
Requires-Dist: pytest-cov>=4.0; extra == "dev"
Requires-Dist: ruff>=0.1.0; extra == "dev"
Requires-Dist: mypy>=1.0; extra == "dev"
Requires-Dist: types-PyYAML>=6.0; extra == "dev"
Provides-Extra: rich
Requires-Dist: rich>=13.0; extra == "rich"
Dynamic: license-file
